LICENSE.txt
README.md
pyproject.toml
setup.cfg
setup.py
naiveautoml/__init__.py
naiveautoml/_interfaces.py
naiveautoml/commons.py
naiveautoml/evaluators.py
naiveautoml/naiveautoml.py
naiveautoml/searchspace-classification.json
naiveautoml/searchspace-regression.json
naiveautoml.egg-info/PKG-INFO
naiveautoml.egg-info/SOURCES.txt
naiveautoml.egg-info/dependency_links.txt
naiveautoml.egg-info/requires.txt
naiveautoml.egg-info/top_level.txt
naiveautoml/algorithm_selection/__init__.py
naiveautoml/algorithm_selection/_pipeline.py
naiveautoml/algorithm_selection/_sklearn_factory.py
naiveautoml/algorithm_selection/_sklearn_hpo.py
naiveautoml/algorithm_selection/sklearn.py
naiveautoml/hpo/__init__.py
naiveautoml/hpo/random_search.py
test/test_naiveautoml.py